cohesive/__init__.py
cohesive/auth.py
cohesive/error.py
cohesive/params.py
cohesive/api_resources/__init__.py
cohesive/api_resources/usage.py
cohesive_marketplace_server_sdk_python-1.0.2.dist-info/LICENSE
cohesive_marketplace_server_sdk_python-1.0.2.dist-info/METADATA
cohesive_marketplace_server_sdk_python-1.0.2.dist-info/WHEEL
cohesive_marketplace_server_sdk_python-1.0.2.dist-info/top_level.txt
cohesive_marketplace_server_sdk_python-1.0.2.dist-info/RECORD
