Metadata-Version: 2.1
Name: cohesive-marketplace-server-sdk-python
Version: 1.0.2
Summary: Python bindings for the Cohesive Marketplace API
Home-page: https://github.com/getcohesive/marketplace-server-sdk-python
Author: Cohesive
Author-email: Team Cohesive <contact@cohesive.so>
License: MIT
Project-URL: Source Code, https://github.com/getcohesive/marketplace-server-sdk-python
Keywords: cohesive api marketplace saas
Classifier: Development Status :: 5 - Production/Stable
Classifier: Intended Audience :: Developers
Classifier: License :: OSI Approved :: MIT License
Classifier: Operating System :: OS Independent
Classifier: Programming Language :: Python
Classifier: Programming Language :: Python :: 3.7
Classifier: Programming Language :: Python :: 3.8
Classifier: Programming Language :: Python :: 3.9
Classifier: Programming Language :: Python :: 3.10
Classifier: Programming Language :: Python :: Implementation :: PyPy
Classifier: Topic :: Software Development :: Libraries :: Python Modules
Requires-Python: >=3.7
License-File: LICENSE
Requires-Dist: requests (>=2.28.2)
Requires-Dist: PyJWT (>=2.6.0)
